labchart_tools
test
