Metadata-Version: 2.1
Name: labchart-tools
Version: 0.0.5
Summary: Package for processing data exported as txt files from ADInstruments LabChart
Home-page: https://github.com/jwgerlach00/labchart_tools
Author: Jacob Gerlach
Author-email: jwgerlach00@gmail.com
License: MIT
Platform: UNKNOWN
Requires-Python: >=3.6
